Workbook

Sheet RFI Triggers
A1: Common RFI trigger | B1: Category | C1: How frequent it backfires | D1: Resolution | E1: How painful the resolution is today | F1: Urgency | G1: What data would reflect it
A2: Transaction Amount > $10,000 USD | B2: Amount deviation | C2: Daily | D2: Compliance analyst manually reviews transaction and requests invoice or source-of-funds proof from client | E2: High — funds frozen 24h+; client scrambles for invoices; compliance absorbs manual back-and-forth | F2: High | G2: ='Transaction Data'!D4 -> Wire transfer - Sender data - Amount USD
A3: Transaction Amount deviated by + $10,000 USD and 40% | B3: Amount deviation | C3: Weekly | D3: Compliance analyst requests justification for deviation; client submits supporting docs manually | E3: High — client must reconstruct deviation context; no pre-collected baseline for comparison | F3: High | G3: ='Transaction Data'!D27 -> Receiver bank records - Receiver data - previous trasfer
A4: receivers last 30 days total transactions income above X | B4: Amount deviation | C4: Daily | D4: Compliance reviews income history; client provides bank statements or payroll records | E4: Medium — bank statements are obtainable but slow; no automated income baseline exists | F4: Medium | G4: ='Transaction Data'!D29 -> Receiver bank records - Receiver data - amount of trasfers
A5: receivers last 30 days transaction income deviated by + $x and y% | B5: Amount deviation | C5: Weekly | D5: Client explains deviation pattern; compliance cross-checks with prior transaction history manually | E5: Medium — pattern context is available internally but requires manual cross-check | F5: Medium | G5: ='Transaction Data'!D29 -> Receiver bank records - Receiver data - amount of trasfers
A6: Sender bank country in high risk list | B6: High risk sender | C6: Weekly | D6: Compliance officer escalates; transaction flagged, client asked to justify sender bank origin | E6: High — requires compliance officer escalation; client has no control over sender bank's risk classification | F6: High | G6: ='Transaction Data'!D3&" (Available black lists)" -> Wire transfer - Sender data - Bank Adress (Available black lists)
A7: Sender bank registered as high-risk | B7: High risk sender | C7: Monthly | D7: Transaction frozen; compliance verifies bank registration against external risk databases manually | E7: High — client cannot easily change their sender's bank; resolution may require dropping the counterparty | F7: High | G7: ='Transaction Data'!D3 -> Wire transfer - Sender data - Bank Adress
A8: Sender IBAN flagged externally | B8: High risk sender | C8: Monthly | D8: Compliance analyst cross-checks IBAN against external flagging databases; client asked to explain sender relationship | E8: High — external flag origin often opaque; client has no self-service way to contest or explain | F8: High | G8: ='Transaction Data'!D2 -> Wire transfer - Sender data - Bank name
A9: sender adress in high risk neighberhood | B9: High risk sender | C9: Weekly | D9: Client asked to justify sender address; compliance manually assesses geo-risk with no automated tool | E9: Medium — client can provide address context but geo-risk scoring is entirely manual and inconsistent | F9: Medium | G9: ="AI can classify"&" "&'Transaction Data'!D13 -> AI can classify Wire transfer - Sender data - Sender address
A10: + 3 receiving bank accounts receiving funds from same sender bank | B10: High risk sender | C10: Monthly | D10: Compliance analyst maps network manually; client asked to explain all related senders | E10: High — mapping 3+ related accounts is time-consuming; no automated network visualization tool in place | F10: Medium | G10: ='Transaction Data'!D16 -> Receiver bank records - Receiver data - Behavior Risk
A11: Transaction time between 10 pm and 4 am in sender bank local time | B11: High risk sender | C11: Daily | D11: Transaction flagged for off-hours activity; compliance reviews next business day, funds held overnight | E11: Medium — client has no control over sender timing; funds held until next business day review | F11: Low | G11: ='Transaction Data'!D12 -> Wire transfer - Sender data - time
A12: Receiver account created less than 30 days ago | B12: New account | C12: Monthly | D12: Compliance requests account history and proof of account age; client contacts beneficiary to provide docs | E12: Medium — account age is verifiable but requires reaching the beneficiary who may be unresponsive | F12: Medium | G12: ='Transaction Data'!D37 -> Receiver bank records - Receiver data - Creation date
A13: Sender IBAN flagged internally | B13: Previously flagged sender | C13: Weekly | D13: Internal flag surfaced during review; compliance analyst validates against internal watchlist | E13: Low — internal flag is already known; resolution is primarily process confirmation | F13: High | G13: ='Transaction Data'!D34 -> Receiver bank records - Receiver data - Banned sender IBAN
A14: Receiver account has missing information | B14: Receiver has missing documents | C14: Weekly | D14: Client contacted to request missing beneficiary documents; funds frozen until received | E14: High — missing docs require outreach to beneficiary; completion timeline is unpredictable | F14: High | G14: ='Transaction Data'!D25 -> Receiver bank records - Receiver data - creation data
A15: Receiver account has expired documents | B15: Receiver has missing documents | C15: Monthly | D15: Compliance requests renewed documents from client; funds frozen until expiry resolved | E15: Medium — document renewal is straightforward but introduces compliance delay and client frustration | F15: Medium | G15: ='Transaction Data'!D25 -> Receiver bank records - Receiver data - creation data
A16: Receiver account flagged as Politically Exposed Person | B16: sanctions/PEP hits | C16: Monthly | D16: Transaction escalated to compliance officer; PEP status verified against external registry | E16: High — PEP status is binary and hard to overturn; escalation adds days to resolution | F16: High | G16: ='Transaction Data'!D25 -> Receiver bank records - Receiver data - creation data
A17: Sender or receiver in international black list (Interpol, Clinton List, etc.) | B17: sanctions/PEP hits | C17: Monthly | D17: Transaction immediately frozen; compliance cross-checks sender/receiver against Interpol, Clinton and other lists | E17: Very High — sanctions hits trigger mandatory holds; resolution requires legal and compliance officer review | F17: Critical | G17: ='Transaction Data'!D36 -> External records - Sender data - Sanctioned person or organization (Interpol, Clinton List)
A18: Sender or receiver bank from sanctioned country | B18: sanctions/PEP hits | C18: Monthly | D18: Funds frozen; compliance re-verifies bank origin, escalates to compliance officer for sign-off | E18: Very High — same as above; duplicate risk when both sender and receiver bank are flagged | F18: Critical | G18: ='Transaction Data'!D35 -> External records - Sender data - Sanctioned country
A19: Low income receiver status (unemployed or student) | B19: Suspicious receiver account activity | C19: Weekly | D19: Client asked to justify receiver's income status; compliance requests employment or student documentation | E19: Medium — client can provide income docs but beneficiary may resist sharing personal status information | F19: Low | G19: ='Transaction Data'!D25 -> Receiver bank records - Receiver data - creation data
A20: Receiver Dormant (+X days) account suddenly active | B20: Suspicious receiver account activity | C20: Monthly | D20: Compliance reviews account activity history; client asked to explain sudden reactivation and source of incoming funds | E20: Medium — dormancy context is available in transaction history but requires manual investigation | F20: Medium | G20: ='Transaction Data'!D27 -> Receiver bank records - Receiver data - previous trasfer
A42: Sancion/PEP hits
A43: Industry-risk mismatch
A44: behavioral anomalies

Sheet Transaction Data
A1: Source | B1: Party | C1: Variable measured | D1: complete
A2: Wire transfer | B2: Sender data | C2: Bank name | D2: =A2&" - "&B2&" - "&C2 -> Wire transfer - Sender data - Bank name
A3: Wire transfer | B3: Sender data | C3: Bank Adress | D3: =A3&" - "&B3&" - "&C3 -> Wire transfer - Sender data - Bank Adress
A4: Wire transfer | B4: Sender data | C4: Amount USD | D4: =A4&" - "&B4&" - "&C4 -> Wire transfer - Sender data - Amount USD
A5: Wire transfer | B5: Sender data | C5: First transaction date | D5: =A5&" - "&B5&" - "&C5 -> Wire transfer - Sender data - First transaction date
A6: Wire transfer | B6: Sender data | C6: Deviation from | D6: =A6&" - "&B6&" - "&C6 -> Wire transfer - Sender data - Deviation from
A7: Wire transfer | B7: Sender data | C7: Sender Iban | D7: =A7&" - "&B7&" - "&C7 -> Wire transfer - Sender data - Sender Iban
A8: Wire transfer | B8: Sender data | C8: Sender full name | D8: =A8&" - "&B8&" - "&C8 -> Wire transfer - Sender data - Sender full name
A9: Wire transfer | B9: Sender data | C9: currency | D9: =A9&" - "&B9&" - "&C9 -> Wire transfer - Sender data - currency
A10: Wire transfer | B10: Sender data | C10: payment reference | D10: =A10&" - "&B10&" - "&C10 -> Wire transfer - Sender data - payment reference
A11: Wire transfer | B11: Sender data | C11: date | D11: =A11&" - "&B11&" - "&C11 -> Wire transfer - Sender data - date
A12: Wire transfer | B12: Sender data | C12: time | D12: =A12&" - "&B12&" - "&C12 -> Wire transfer - Sender data - time
A13: Wire transfer | B13: Sender data | C13: Sender address | D13: =A13&" - "&B13&" - "&C13 -> Wire transfer - Sender data - Sender address
... A37: Receiver bank records | B37: Receiver data | C37: Creation date | D37: =A37&" - "&B37&" - "&C37 -> Receiver bank records - Receiver data - Creation date
